distributo
