Metadata-Version: 1.0
Name: distributo
Version: 0.1.2
Summary: Probabilistic distributions
Home-page: UNKNOWN
Author: Sebastian Barzaghi
Author-email: UNKNOWN
License: UNKNOWN
Platform: UNKNOWN
